README.rst
jpmesh.py
setup.py
pyjpmesh.egg-info/PKG-INFO
pyjpmesh.egg-info/SOURCES.txt
pyjpmesh.egg-info/dependency_links.txt
pyjpmesh.egg-info/top_level.txt
test/test_angle.py
test/test_coordinate.py
test/test_mesh.py